nest_joblib/__init__.py
nest_joblib/_main.py
nest_joblib/py.typed
nest_joblib-0.1.7.dist-info/LICENSE
nest_joblib-0.1.7.dist-info/METADATA
nest_joblib-0.1.7.dist-info/WHEEL
nest_joblib-0.1.7.dist-info/RECORD
