Metadata-Version: 2.1
Name: nest-joblib
Version: 0.1.7
Summary: Patch joblib to allow nested parallelism
Home-page: https://github.com/34j/nest-joblib
License: MIT
Author: 34j
Author-email: 34j.95a2p@simplelogin.com
Requires-Python: >=3.8,<4.0
Classifier: Development Status :: 2 - Pre-Alpha
Classifier: Intended Audience :: Developers
Classifier: License :: OSI Approved :: MIT License
Classifier: Natural Language :: English
Classifier: Operating System :: OS Independent
Classifier: Programming Language :: Python :: 3
Classifier: Programming Language :: Python :: 3.8
Classifier: Programming Language :: Python :: 3.9
Classifier: Programming Language :: Python :: 3.10
Classifier: Programming Language :: Python :: 3.11
Classifier: Programming Language :: Python :: 3.12
Classifier: Programming Language :: Python :: 3.13
Classifier: Topic :: Software Development :: Libraries
Requires-Dist: joblib (>=1)
Requires-Dist: typing-extensions (>=4)
Project-URL: Bug Tracker, https://github.com/34j/nest-joblib/issues
Project-URL: Changelog, https://github.com/34j/nest-joblib/blob/main/CHANGELOG.md
Project-URL: Documentation, https://nest-joblib.readthedocs.io
Project-URL: Repository, https://github.com/34j/nest-joblib
